rfiletype-0.2.2.dist-info/METADATA
rfiletype-0.2.2.dist-info/WHEEL
rfiletype/__init__.py
rfiletype/__init__.pyi
rfiletype/py.typed
rfiletype/rfiletype.abi3.so
rfiletype-0.2.2.dist-info/RECORD
