Metadata-Version: 2.1
Name: rfiletype
Version: 0.2.2
Summary: infer file and MIME type by checking the magic number signature
Author: messense <messense@icloud.com>
Author-email: messense <messense@icloud.com>
License: MIT
Project-URL: Source Code, https://github.com/messense/rfiletype-py
